shakuapi/__init__.py
shakuapi/auth.py
shakuapi/client.py
shakuapi/services.py
shakuapi-0.2.0.dist-info/LICENSE
shakuapi-0.2.0.dist-info/METADATA
shakuapi-0.2.0.dist-info/WHEEL
shakuapi-0.2.0.dist-info/top_level.txt
shakuapi-0.2.0.dist-info/RECORD
