Metadata-Version: 2.1
Name: shakuapi
Version: 0.2.0
Summary: A simple Python SDK for Shaku REST APIs (size measurement & clothes recognition)
Home-page: UNKNOWN
Author: Shaku
License: UNKNOWN
Platform: UNKNOWN
Classifier: Programming Language :: Python :: 3
Classifier: License :: OSI Approved :: MIT License
Classifier: Operating System :: OS Independent
Requires-Python: >=3.6
License-File: LICENSE
Requires-Dist: requests
